shaksz/__init__.py
shaksz/codeforces.py
shaksz/leetcode.py
shaksz-0.1.4.dist-info/LICENSE
shaksz-0.1.4.dist-info/METADATA
shaksz-0.1.4.dist-info/WHEEL
shaksz-0.1.4.dist-info/top_level.txt
shaksz-0.1.4.dist-info/RECORD
