Metadata-Version: 2.1
Name: shaksz
Version: 0.1.4
Summary: All coding and design solutions as package
Home-page: https://github.com/vermavarun/shaksz
Author: Varun Verma
Author-email: vermavarun@outlook.com
License: UNKNOWN
Platform: UNKNOWN
Classifier: Programming Language :: Python :: 3
Classifier: License :: OSI Approved :: MIT License
Classifier: Operating System :: OS Independent
Requires-Python: >=3.6
